solution_efe_client_user/__init__.py
solution_efe_client_user/userService.py
solution_efe_client_user-1.0.2.dist-info/METADATA
solution_efe_client_user-1.0.2.dist-info/WHEEL
solution_efe_client_user-1.0.2.dist-info/top_level.txt
solution_efe_client_user-1.0.2.dist-info/RECORD
